pyuploader/__init__.py
pyuploader/driver.py
pyuploader/common/__init__.py
pyuploader/common/gateways.py
pyuploader/common/logconfig.py
pyuploader/common/utils.py
pyuploader/errorhandling/__init__.py
pyuploader/errorhandling/appexceptions.py
pyuploader/uploaders/__init__.py
pyuploader/uploaders/file_uploader.py
pyuploader/uploaders/triple_store_uploader.py
pyuploader/uploaders/uploader.py
pyuploader/uploaders/uploader_factory.py
pyuploader-1.2.0.dist-info/LICENSE
pyuploader-1.2.0.dist-info/METADATA
pyuploader-1.2.0.dist-info/WHEEL
pyuploader-1.2.0.dist-info/entry_points.txt
pyuploader-1.2.0.dist-info/top_level.txt
pyuploader-1.2.0.dist-info/RECORD
