Metadata-Version: 2.1
Name: pyuploader
Version: 1.2.0
Summary: pyuploader is a simple command line tool for uploading data to a triple store and a file server.
Home-page: https://github.com/cambridge-cares/TheWorldAvatar/tree/develop/JPS_BASE_LIB/python_uploader
Author: Daniel Nurkowski
Author-email: danieln@cmclinnovations.com
License: MIT
Platform: UNKNOWN
Requires-Python: >=3.5
Requires-Dist: py4jps (>=1.0.18)
Requires-Dist: docopt
Requires-Dist: requests
